visibl/__init__.py
visibl/backend.py
visibl/cli.py
visibl/server.py
visibl/dist/visibl_cli
visibl-1.0.0.data/data/visibl_cli
visibl-1.0.0.data/scripts/visibl.sh
visibl-1.0.0.dist-info/METADATA
visibl-1.0.0.dist-info/WHEEL
visibl-1.0.0.dist-info/entry_points.txt
visibl-1.0.0.dist-info/top_level.txt
visibl-1.0.0.dist-info/RECORD
