Metadata-Version: 2.1
Name: visibl
Version: 1.0.0
Summary: A CLI tool for Visibl
Home-page: UNKNOWN
Author: Visibl Semiconductors
License: UNKNOWN
Platform: macosx_10_9_x86_64
Classifier: Development Status :: 4 - Beta
Classifier: Intended Audience :: Developers
Classifier: Operating System :: OS Independent
Classifier: Programming Language :: Python :: 3
Classifier: Programming Language :: Python :: 3.7
Classifier: Programming Language :: Python :: 3.8
Classifier: Programming Language :: Python :: 3.9
Classifier: Programming Language :: Python :: 3.10
Requires-Python: >=3.7
Requires-Dist: click>=7.0
